{
    "version": "0.6.4",
    "architecture": {
        "64bit": {
            "url": "https://github.com/gitsocial-org/gitsocial/releases/download/v0.6.4/gitsocial_0.6.4_windows_amd64.zip",
            "bin": [
                "gitsocial.exe"
            ],
            "hash": "d86f9428eb9ca21fb7178601517135188abe8ffda152919532b1db0673add348"
        }
    },
    "homepage": "https://github.com/gitsocial-org/gitsocial",
    "license": "MIT",
    "description": "Git-native collaboration — posts, issues, PRs, releases, all in your repo"
}
